pandusx/__init__.py
pandusx/main.py
pandusx-0.1.31.dist-info/METADATA
pandusx-0.1.31.dist-info/WHEEL
pandusx-0.1.31.dist-info/top_level.txt
pandusx-0.1.31.dist-info/RECORD
