Metadata-Version: 2.4
Name: pandusx
Version: 0.1.31
Summary: Pandus package for koding
Author: Your Name
Requires-Python: >=3.6
Dynamic: author
Dynamic: requires-python
Dynamic: summary
